HISTORY.txt
README.txt
TODO.txt
setup.cfg
setup.py
prdg/__init__.py
prdg.plone.testing.egg-info/PKG-INFO
prdg.plone.testing.egg-info/SOURCES.txt
prdg.plone.testing.egg-info/dependency_links.txt
prdg.plone.testing.egg-info/entry_points.txt
prdg.plone.testing.egg-info/namespace_packages.txt
prdg.plone.testing.egg-info/not-zip-safe
prdg.plone.testing.egg-info/requires.txt
prdg.plone.testing.egg-info/top_level.txt
prdg/plone/__init__.py
prdg/plone/configure.zcml
prdg/plone/testing.py