Metadata-Version: 1.0
Name: prdg.plone.testing
Version: 0.0.6
Summary: Provide useful base classes for testing in Plone.
Home-page: http://code.google.com/p/prdg-python/
Author: Rafael Oliveira
Author-email: rafaelbco@gmail.com
License: GPL
Keywords: plone testing TestCase
Platform: UNKNOWN
Classifier: Programming Language :: Python
Classifier: Topic :: Software Development :: Libraries :: Python Modules
